{
    "0": [
        "1k5n",
        "3mre",
        "7r7w",
        "3d25",
        "3mrg",
        "7kgq",
        "6j2a",
        "1x7q",
        "7m8t",
        "7wkj",
        "6j1w",
        "5eu5",
        "7kgr",
        "5nmh",
        "7kgs",
        "5wmr",
        "6o4y",
        "2vll",
        "2v2w",
        "5wmo",
        "7p3d",
        "4qrq",
        "5e00",
        "5txs",
        "3mrd",
        "3l3i",
        "7ejm",
        "1uxw",
        "5w6a",
        "3d18",
        "2cik",
        "4u1s",
        "4hx1",
        "3x12",
        "5vue",
        "3bp7",
        "5vwf",
        "1i7u",
        "5iek",
        "3l3d",
        "1duz",
        "3x13",
        "5wmn",
        "4nt6",
        "3kpq",
        "5enw",
        "3bxn",
        "3myj",
        "5vuf",
        "3ft4",
        "6d2t",
        "6uzs",
        "3kpp",
        "4nny",
        "5ib1",
        "4u1i",
        "3fqw",
        "3kpl",
        "7l1c",
        "7lgt",
        "4o2e",
        "3kpn",
        "3lkr",
        "5vvp",
        "4nqx",
        "6j1v",
        "5vud",
        "3v5d",
        "6z9v",
        "7l1b",
        "2bst",
        "7ejn",
        "3x11",
        "6o9b",
        "1e27",
        "7mle",
        "7nmd",
        "7lg0",
        "1xr8",
        "1a1m",
        "2x4o",
        "3mrf",
        "1eez",
        "7n6d",
        "7tlt",
        "6vr5",
        "2c7u",
        "4hwz",
        "6uzq",
        "1qr1",
        "3mrl",
        "6o9c",
        "5xs3",
        "1hhi",
        "5f9j",
        "6ujq",
        "1hhg",
        "1cg9",
        "2bck",
        "5w69",
        "7n1b",
        "5inc",
        "7s8r"
    ],
    "9": [
        "4u1m",
        "4u1n",
        "1xr9",
        "6uli",
        "6jtp",
        "4u1k",
        "5vge"
    ],
    "16": [
        "3czf",
        "5wmq",
        "5ib2",
        "1uxs",
        "1m05",
        "7nui",
        "3bvn"
    ],
    "42": [
        "6y26",
        "6y2a",
        "6y27",
        "6pyj",
        "6y28"
    ],
    "3": [
        "6mt3",
        "1a9b"
    ],
    "56": [
        "7tuc",
        "3kpm",
        "1syv",
        "3h7b",
        "4k7f",
        "1t1y",
        "1t20",
        "3mrh",
        "5ib5",
        "3l3k",
        "7eu2"
    ],
    "41": [
        "6y29",
        "6y2b",
        "7lg3"
    ],
    "2": [
        "6mt6",
        "6mt5",
        "6mt4",
        "7r7y",
        "4qru",
        "3skm",
        "3x14",
        "5ind"
    ],
    "20": [
        "2bvp",
        "7jyv",
        "6vr1"
    ],
    "28": [
        "6mtl",
        "3lv3"
    ],
    "27": [
        "6joz",
        "3rew"
    ],
    "45": [
        "6pyw",
        "6pyv",
        "6pz5",
        "1hsa",
        "1jge",
        "1i7r",
        "1b0g",
        "2x4s",
        "1i7t"
    ],
    "32": [
        "4u1j",
        "6vb1",
        "5eo1",
        "2x4u",
        "1i1y",
        "1i1f"
    ],
    "12": [
        "4qrs",
        "4qrt"
    ],
    "51": [
        "3mrk",
        "7sa2",
        "3ixa",
        "6ss9"
    ],
    "21": [
        "7kgp",
        "1sys",
        "3to2",
        "6z9w",
        "7f4w"
    ],
    "7": [
        "2a83",
        "5im7"
    ],
    "35": [
        "3mrb",
        "3gsr"
    ],
    "18": [
        "6vb2",
        "6vb0"
    ],
    "29": [
        "7m8u",
        "3lko",
        "3lkp",
        "3lkq"
    ],
    "37": [
        "1ogt",
        "5def",
        "5deg",
        "5ib3",
        "5ib4",
        "1of2"
    ],
    "53": [
        "6q3k",
        "3gso",
        "3gsu",
        "7u21",
        "3gsv",
        "3mr9",
        "3ft3",
        "3gsx",
        "3gsq",
        "1t22",
        "5meq",
        "3kpo"
    ],
    "50": [
        "6o4z",
        "1t1z",
        "7kgo"
    ],
    "31": [
        "4u1h",
        "5eo0"
    ],
    "6": [
        "2v2x",
        "7lg2"
    ],
    "8": [
        "6v2q",
        "3bp4",
        "4u1l"
    ],
    "24": [
        "6j29",
        "5vwd",
        "3hpj",
        "4nqv"
    ],
    "46": [
        "1m6o",
        "7ejl",
        "6pte",
        "3l3g",
        "1s8d",
        "1t1w",
        "2x4r"
    ],
    "38": [
        "3pwn",
        "3pwl",
        "3pwj"
    ],
    "17": [
        "3sko",
        "7mja",
        "3mrc",
        "3mri",
        "6xqa",
        "1a9e",
        "7jyw"
    ],
    "19": [
        "7r7v",
        "5vwh",
        "5vwj",
        "7r7x",
        "2rfx"
    ],
    "47": [
        "3v5h",
        "6opd",
        "7mkb",
        "7uc5",
        "5hhn",
        "7rtd",
        "5hhq",
        "3v5k",
        "7re8"
    ],
    "48": [
        "3kla",
        "1s9w",
        "1s9y",
        "3l3j",
        "1s9x"
    ],
    "49": [
        "5nmk",
        "7mj9",
        "7mj6",
        "4l3c"
    ],
    "23": [
        "3qfd",
        "2gtz",
        "1jht"
    ],
    "52": [
        "5xos",
        "1hhj"
    ],
    "34": [
        "2git",
        "2av1",
        "2av7",
        "1hhk"
    ],
    "43": [
        "1n2r",
        "3lks",
        "3lkn",
        "7lgd"
    ],
    "25": [
        "5n6b",
        "6ssa",
        "6ss8"
    ],
    "15": [
        "4i4w",
        "5meo",
        "7lfz",
        "3i6l",
        "5mep"
    ],
    "30": [
        "1tvb",
        "3fqt",
        "1tvh",
        "5eu3",
        "5eu4"
    ],
    "14": [
        "6uzm",
        "2h6p",
        "6vb7",
        "6vb6",
        "6vb5",
        "6uzn"
    ],
    "22": [
        "3bo8",
        "1w0v"
    ],
    "4": [
        "3gsw",
        "5fa3"
    ],
    "36": [
        "3mrj",
        "2xpg"
    ],
    "11": [
        "3c9n",
        "6viu",
        "6vb4",
        "6uzo"
    ],
    "33": [
        "5mer",
        "4l29"
    ],
    "54": [
        "5hhp",
        "1t1x"
    ],
    "26": [
        "2guo",
        "1q94",
        "6ss7"
    ],
    "13": [
        "6vb3",
        "6uzp"
    ],
    "5": [
        "3upr",
        "6ujo"
    ],
    "40": [
        "5wsh",
        "3rl1",
        "6ptb"
    ],
    "55": [
        "3h9h",
        "1t21",
        "1eey"
    ],
    "44": [
        "7p3e",
        "7n1a",
        "1qew",
        "2bsr"
    ],
    "10": [
        "5u98",
        "1w0w",
        "1a1o",
        "4i48"
    ],
    "39": [
        "4no5",
        "6nca"
    ],
    "1": [
        "5vgd",
        "1qqd"
    ]
}